djangosavebyattributes/__init__.py
djangosavebyattributes/instance_methods.py
djangosavebyattributes-0.1.0.dist-info/LICENSE.md
djangosavebyattributes-0.1.0.dist-info/METADATA
djangosavebyattributes-0.1.0.dist-info/WHEEL
djangosavebyattributes-0.1.0.dist-info/top_level.txt
djangosavebyattributes-0.1.0.dist-info/RECORD
