Metadata-Version: 2.1
Name: djangosavebyattributes
Version: 0.1.0
Summary: Helps to save instance by providing attribute mapping hash
Home-page: UNKNOWN
Author: Me
License: MIT
Platform: UNKNOWN
License-File: LICENSE.md
Requires-Dist: Django
